scsm/__init__.py
scsm/cli.py
scsm/config.py
scsm/core.py
scsm/data/.git
scsm/data/LICENSE
scsm/data/README.md
scsm/data/apps/105600.yaml
scsm/data/apps/111710.yaml
scsm/data/apps/17505.yaml
scsm/data/apps/17515.yaml
scsm/data/apps/17575.yaml
scsm/data/apps/211820.yaml
scsm/data/apps/215350.yaml
scsm/data/apps/215360.yaml
scsm/data/apps/222840.yaml
scsm/data/apps/222860.yaml
scsm/data/apps/223249.yaml
scsm/data/apps/223250.yaml
scsm/data/apps/228780.yaml
scsm/data/apps/232250.yaml
scsm/data/apps/232290.yaml
scsm/data/apps/232330.yaml
scsm/data/apps/232370.yaml
scsm/data/apps/233780.yaml
scsm/data/apps/237410.yaml
scsm/data/apps/244310.yaml
scsm/data/apps/255470.yaml
scsm/data/apps/258550.yaml
scsm/data/apps/261140.yaml
scsm/data/apps/270150.yaml
scsm/data/apps/294420.yaml
scsm/data/apps/295230.yaml
scsm/data/apps/310.yaml
scsm/data/apps/312070.yaml
scsm/data/apps/313900.yaml
scsm/data/apps/317670.yaml
scsm/data/apps/317800.yaml
scsm/data/apps/332670.yaml
scsm/data/apps/332850.yaml
scsm/data/apps/338440.yaml
scsm/data/apps/343050.yaml
scsm/data/apps/346680.yaml
scsm/data/apps/349090.yaml
scsm/data/apps/376030.yaml
scsm/data/apps/380840.yaml
scsm/data/apps/380870.yaml
scsm/data/apps/383410.yaml
scsm/data/apps/4020.yaml
scsm/data/apps/403240.yaml
scsm/data/apps/405100.yaml
scsm/data/apps/41080.yaml
scsm/data/apps/416880.yaml
scsm/data/apps/427520.yaml
scsm/data/apps/443030.yaml
scsm/data/apps/460040.yaml
scsm/data/apps/462310.yaml
scsm/data/apps/475370.yaml
scsm/data/apps/4940.yaml
scsm/data/apps/497110.yaml
scsm/data/apps/581330.yaml
scsm/data/apps/629800.yaml
scsm/data/apps/739590.yaml
scsm/data/apps/740.yaml
scsm/data/apps/90.yaml
scsm/scsm-complete.sh
scsm-0.2.8.dist-info/LICENSE
scsm-0.2.8.dist-info/WHEEL
scsm-0.2.8.dist-info/entry_points.txt
scsm-0.2.8.dist-info/METADATA
scsm-0.2.8.dist-info/RECORD
